pydolce/__init__.py
pydolce/config.py
pydolce/main.py
pydolce/commands/check.py
pydolce/commands/restyle.py
pydolce/commands/suggest.py
pydolce/core/check.py
pydolce/core/client.py
pydolce/core/errors.py
pydolce/core/parser.py
pydolce/core/suggest.py
pydolce/core/utils.py
pydolce/core/rules/rules.py
pydolce/core/rules/checkers/_1xx_structural.py
pydolce/core/rules/checkers/_2xx_style.py
pydolce/core/rules/checkers/_3xx_signature.py
pydolce/core/rules/checkers/_4xx_content.py
pydolce/core/rules/checkers/_6xx_semantic.py
pydolce/core/rules/checkers/__init__.py
pydolce-0.1.5.dist-info/licenses/LICENSE
pydolce-0.1.5.dist-info/METADATA
pydolce-0.1.5.dist-info/WHEEL
pydolce-0.1.5.dist-info/entry_points.txt
pydolce-0.1.5.dist-info/top_level.txt
pydolce-0.1.5.dist-info/RECORD
