Metadata-Version: 2.4
Name: pydolce
Version: 0.1.5
Summary: The sweet way to catch outdated docstrings
Author-email: Jorge Morgado Vega <jorge.morgadov@gmail.com>
License: MIT
Requires-Python: >=3.10
License-File: LICENSE
Requires-Dist: rich
Requires-Dist: requests
Requires-Dist: typer
Requires-Dist: toml
Requires-Dist: docstring-parser
Dynamic: license-file
